MANIFEST.in
README.rst
setup.cfg
setup.py
docs/HISTORY.rst
docs/INSTALL.txt
docs/LICENSE.GPL
docs/LICENSE.txt
src/rt/__init__.py
src/rt.zestreleaser.pyflakes.egg-info/PKG-INFO
src/rt.zestreleaser.pyflakes.egg-info/SOURCES.txt
src/rt.zestreleaser.pyflakes.egg-info/dependency_links.txt
src/rt.zestreleaser.pyflakes.egg-info/entry_points.txt
src/rt.zestreleaser.pyflakes.egg-info/namespace_packages.txt
src/rt.zestreleaser.pyflakes.egg-info/not-zip-safe
src/rt.zestreleaser.pyflakes.egg-info/requires.txt
src/rt.zestreleaser.pyflakes.egg-info/top_level.txt
src/rt/zestreleaser/__init__.py
src/rt/zestreleaser/pyflakes/__init__.py
src/rt/zestreleaser/pyflakes/pyflakes_checker.py
src/rt/zestreleaser/pyflakes/tests/__init__.py
src/rt/zestreleaser/pyflakes/tests/test_pyflakes.py
src/rt/zestreleaser/pyflakes/tests/data/a.py
src/rt/zestreleaser/pyflakes/tests/data/b.py