Metadata-Version: 1.1
Name: rt.zestreleaser.pyflakes
Version: 0.1.0
Summary: Plugin for zest.releaser to allow check your Python code with Pyflakes before making a release
Home-page: https://github.com/RedTurtle/rt.zestreleaser.pyflakes
Author: RedTurtle Technology
Author-email: keul@redturtle.it
License: GPL
Keywords: releaser zest.releaser egg pyflakes
Platform: UNKNOWN
Classifier: Programming Language :: Python
Classifier: Environment :: Console
Classifier: Environment :: Plugins
Classifier: Intended Audience :: Developers
Classifier: Topic :: Software Development
Classifier: Topic :: System :: Archiving :: Packaging
Classifier: Topic :: System :: Installation/Setup
Classifier: Topic :: Utilities
